{
  "minecraft:recipes/decorations/crafting_table": {
    "criteria": {
      "unlock_right_away": "2024-01-15 16:52:09 -0500"
    },
    "done": true
  },
  "minecraft:adventure/adventuring_time": {
    "criteria": {
      "minecraft:taiga": "2024-01-15 16:52:28 -0500",
      "minecraft:frozen_river": "2024-01-15 16:52:29 -0500",
      "minecraft:savanna_plateau": "2024-01-15 21:38:06 -0500",
      "minecraft:beach": "2024-01-15 21:32:24 -0500",
      "minecraft:snowy_taiga": "2024-01-15 16:52:11 -0500",
      "minecraft:forest": "2024-01-15 21:32:31 -0500",
      "minecraft:old_growth_spruce_taiga": "2024-01-15 21:32:39 -0500",
      "minecraft:meadow": "2024-01-15 21:32:26 -0500"
    },
    "done": false
  },
  "minecraft:recipes/misc/white_dye": {
    "criteria": {
      "has_bone_meal": "2024-01-15 16:52:21 -0500"
    },
    "done": true
  },
  "minecraft:recipes/building_blocks/bone_block": {
    "criteria": {
      "has_bone_meal": "2024-01-15 16:52:21 -0500"
    },
    "done": true
  },
  "minecraft:recipes/building_blocks/end_stone_brick_slab_from_end_stone_stonecutting": {
    "criteria": {
      "has_end_stone": "2024-01-15 16:52:46 -0500"
    },
    "done": true
  },
  "minecraft:recipes/building_blocks/end_stone_bricks": {
    "criteria": {
      "has_end_stone": "2024-01-15 16:52:46 -0500"
    },
    "done": true
  },
  "minecraft:recipes/decorations/end_stone_brick_wall_from_end_stone_stonecutting": {
    "criteria": {
      "has_end_stone": "2024-01-15 16:52:46 -0500"
    },
    "done": true
  },
  "minecraft:recipes/building_blocks/end_stone_bricks_from_end_stone_stonecutting": {
    "criteria": {
      "has_end_stone": "2024-01-15 16:52:46 -0500"
    },
    "done": true
  },
  "minecraft:recipes/building_blocks/end_stone_brick_stairs_from_end_stone_stonecutting": {
    "criteria": {
      "has_end_stone": "2024-01-15 16:52:46 -0500"
    },
    "done": true
  },
  "minecraft:recipes/transportation/mangrove_boat": {
    "criteria": {
      "in_water": "2024-01-15 16:53:40 -0500"
    },
    "done": true
  },
  "minecraft:recipes/transportation/acacia_boat": {
    "criteria": {
      "in_water": "2024-01-15 16:53:40 -0500"
    },
    "done": true
  },
  "minecraft:recipes/transportation/cherry_boat": {
    "criteria": {
      "in_water": "2024-01-15 16:53:40 -0500"
    },
    "done": true
  },
  "minecraft:recipes/transportation/bamboo_raft": {
    "criteria": {
      "in_water": "2024-01-15 16:53:40 -0500"
    },
    "done": true
  },
  "minecraft:recipes/transportation/spruce_boat": {
    "criteria": {
      "in_water": "2024-01-15 16:53:40 -0500"
    },
    "done": true
  },
  "minecraft:recipes/transportation/birch_boat": {
    "criteria": {
      "in_water": "2024-01-15 16:53:40 -0500"
    },
    "done": true
  },
  "minecraft:recipes/transportation/oak_boat": {
    "criteria": {
      "in_water": "2024-01-15 16:53:40 -0500"
    },
    "done": true
  },
  "minecraft:recipes/transportation/jungle_boat": {
    "criteria": {
      "in_water": "2024-01-15 16:53:40 -0500"
    },
    "done": true
  },
  "minecraft:recipes/transportation/dark_oak_boat": {
    "criteria": {
      "in_water": "2024-01-15 16:53:40 -0500"
    },
    "done": true
  },
  "minecraft:end/root": {
    "criteria": {
      "entered_end": "2024-01-15 16:57:27 -0500"
    },
    "done": true
  },
  "minecraft:story/enter_the_end": {
    "criteria": {
      "entered_end": "2024-01-15 16:57:27 -0500"
    },
    "done": true
  },
  "outer_end:end/find_end_tower": {
    "criteria": {
      "in_city": "2024-01-15 21:09:59 -0500"
    },
    "done": true
  },
  "minecraft:end/elytra": {
    "criteria": {
      "elytra": "2024-01-15 21:42:24 -0500"
    },
    "done": true
  },
  "minecraft:recipes/decorations/chest": {
    "criteria": {
      "has_lots_of_items": "2024-01-15 23:20:16 -0500"
    },
    "done": true
  },
  "minecraft:nether/netherite_armor": {
    "criteria": {
      "netherite_armor": "2024-01-16 12:57:57 -0500"
    },
    "done": true
  },
  "minecraft:recipes/misc/mojang_banner_pattern": {
    "criteria": {
      "has_enchanted_golden_apple": "2024-01-16 12:58:02 -0500"
    },
    "done": true
  },
  "minecraft:husbandry/balanced_diet": {
    "criteria": {
      "enchanted_golden_apple": "2024-01-16 12:58:06 -0500"
    },
    "done": false
  },
  "minecraft:husbandry/root": {
    "criteria": {
      "consumed_item": "2024-01-16 12:58:06 -0500"
    },
    "done": true
  },
  "minecraft:adventure/root": {
    "criteria": {
      "killed_something": "2024-01-16 12:58:26 -0500"
    },
    "done": true
  },
  "minecraft:adventure/kill_all_mobs": {
    "criteria": {
      "minecraft:enderman": "2024-01-16 12:59:17 -0500"
    },
    "done": false
  },
  "minecraft:adventure/kill_a_mob": {
    "criteria": {
      "minecraft:enderman": "2024-01-16 12:59:17 -0500"
    },
    "done": true
  },
  "minecraft:recipes/building_blocks/purpur_slab": {
    "criteria": {
      "has_purpur_block": "2024-01-16 13:09:40 -0500"
    },
    "done": true
  },
  "minecraft:recipes/decorations/end_crystal": {
    "criteria": {
      "has_ender_eye": "2024-01-16 13:09:40 -0500"
    },
    "done": true
  },
  "minecraft:recipes/building_blocks/purpur_stairs": {
    "criteria": {
      "has_purpur_block": "2024-01-16 13:09:40 -0500"
    },
    "done": true
  },
  "minecraft:recipes/building_blocks/purpur_pillar_from_purpur_block_stonecutting": {
    "criteria": {
      "has_purpur_block": "2024-01-16 13:09:40 -0500"
    },
    "done": true
  },
  "minecraft:recipes/building_blocks/purpur_stairs_from_purpur_block_stonecutting": {
    "criteria": {
      "has_purpur_block": "2024-01-16 13:09:40 -0500"
    },
    "done": true
  },
  "minecraft:recipes/decorations/ender_chest": {
    "criteria": {
      "has_ender_eye": "2024-01-16 13:09:40 -0500"
    },
    "done": true
  },
  "minecraft:recipes/building_blocks/purpur_pillar": {
    "criteria": {
      "has_purpur_block": "2024-01-16 13:09:40 -0500"
    },
    "done": true
  },
  "minecraft:recipes/building_blocks/purpur_slab_from_purpur_block_stonecutting": {
    "criteria": {
      "has_purpur_block": "2024-01-16 13:09:40 -0500"
    },
    "done": true
  },
  "minecraft:husbandry/breed_an_animal": {
    "criteria": {
      "bred": "2024-01-16 13:40:49 -0500"
    },
    "done": true
  },
  "minecraft:end/find_end_city": {
    "criteria": {
      "in_city": "2024-01-16 15:58:06 -0500"
    },
    "done": true
  },
  "DataVersion": 3465
}